[
    {
        "kod": "P80747",
        "popis": "Larsen Monroe"
    },
    {
        "kod": "3105230",
        "popis": "Guadalupe Bean"
    },
    {
        "kod": "5956332045406944970a0153",
        "popis": "Lee Bond"
    },
    {
        "kod": "595633206ac136c3123f6698",
        "popis": "Mcbride Berger"
    },
    {
        "kod": "59563320b694184f8452de43",
        "popis": "Gilda Estes"
    },
    {
        "kod": "59563320f6520e0001bfebe4",
        "popis": "Watts Rodriquez"
    },
    {
        "kod": "59563320aa1405840788e9c4",
        "popis": "Blackwell Peters"
    },
    {
        "kod": "59563320e51dc4c15f7c5425",
        "popis": "Solis Cline"
    },
    {
        "kod": "59563320f0a28a57f6611af5",
        "popis": "Suzette Montgomery"
    },
    {
        "kod": "59563320c28675efe8053bad",
        "popis": "Christi Cortez"
    },
    {
        "kod": "595633206f2b237f813e3310",
        "popis": "Slater Dickerson"
    },
    {
        "kod": "5956332031fa37dd1f57f11b",
        "popis": "Hope Paul"
    },
    {
        "kod": "595633201b104140ebc4d9d3",
        "popis": "Edith Farmer"
    },
    {
        "kod": "P83216",
        "popis": "Ofelia Arnold"
    },
    {
        "kod": "59563320985fc8ed3c5edefe",
        "popis": "Vickie Hewitt"
    },
    {
        "kod": "595633204806ec013fa0b3e7",
        "popis": "Bethany Boyer"
    },
    {
        "kod": "59563320a5d22738d3ee6f6b",
        "popis": "Franklin Ware"
    },
    {
        "kod": "P85687",
        "popis": "Pena Cleveland"
    },
    {
        "kod": "5956332099b4395952452586",
        "popis": "Sherrie Guerrero"
    },
    {
        "kod": "59563320f9b36b0e595aebd0",
        "popis": "Mckenzie Meyers"
    },
    {
        "kod": "595633202698b67d5d8af31d",
        "popis": "Mae Oneil"
    },
    {
        "kod": "P40707",
        "popis": "Shelly Potts"
    },
    {
        "kod": "59563320d1e1ca7a6b0b0d38",
        "popis": "Rodgers Wooten"
    },
    {
        "kod": "59563320a5649f883c65f8b4",
        "popis": "Brooke Bolton"
    },
    {
        "kod": "59563320c5425dbf8a8e191c",
        "popis": "Case Chambers"
    },
    {
        "kod": "595633201b92e339b9d34580",
        "popis": "Alma Olson"
    },
    {
        "kod": "59563320e15c488ca35b59fb",
        "popis": "Janis Medina"
    },
    {
        "kod": "P66599",
        "popis": "Katelyn Wolfe"
    },
    {
        "kod": "595633206275281529aac76d",
        "popis": "Marsh Gomez"
    },
    {
        "kod": "59563320ab0f0508c8cd3dcb",
        "popis": "Mccullough Coleman"
    },
    {
        "kod": "59563320841e6f97ce163d10",
        "popis": "Claire Montoya"
    },
    {
        "kod": "59563320698efde749e16f4f",
        "popis": "Acevedo Marks"
    },
    {
        "kod": "5956332052e49cf6bed05426",
        "popis": "Estrada Trujillo"
    },
    {
        "kod": "59563320ab1a70e1f07563d6",
        "popis": "Moody Stone"
    },
    {
        "kod": "595633202d7cce7adb7e4542",
        "popis": "Wyatt Booth"
    },
    {
        "kod": "59563320dca25a88a6e90586",
        "popis": "Kathrine Huber"
    },
    {
        "kod": "P77017",
        "popis": "Melinda Rush"
    },
    {
        "kod": "N92725",
        "popis": "Rosella Meyer"
    },
    {
        "kod": "P79469",
        "popis": "Michele Duncan"
    },
    {
        "kod": "595633203ce30997481927c6",
        "popis": "Garcia Ray"
    },
    {
        "kod": "59563320c088c6abd49b969d",
        "popis": "Sonja Thornton"
    },
    {
        "kod": "59563320ea97da7350e035a4",
        "popis": "Murphy Mcfadden"
    },
    {
        "kod": "595633201c9d05544782f260",
        "popis": "Macdonald Ayers"
    },
    {
        "kod": "59563320e3d5ad637c57dadb",
        "popis": "Dolores Rosales"
    },
    {
        "kod": "595633201bab97d8ce3976a2",
        "popis": "Anna Moore"
    },
    {
        "kod": "59563320b7a44f5a230975a6",
        "popis": "Sophie Beard"
    },
    {
        "kod": "59563320d2d974927b95608d",
        "popis": "Mack Gallegos"
    },
    {
        "kod": "5956332073a28413843c565e",
        "popis": "Odom Eaton"
    },
    {
        "kod": "5956332007f9a9b6cfb26402",
        "popis": "Travis Robbins"
    },
    {
        "kod": "595633207ad7497635db165c",
        "popis": "Roach Huff"
    },
    {
        "kod": "595633202c83589f5c9bbe66",
        "popis": "Clarissa Weber"
    },
    {
        "kod": "P80747",
        "popis": "Melanie Johns"
    },
    {
        "kod": "595633206e41c88fa23c3114",
        "popis": "Gretchen Garrison"
    },
    {
        "kod": "5956332028c4b32d93a10296",
        "popis": "Kathy Stephens"
    },
    {
        "kod": "595633200e3cecfaa9ba6eea",
        "popis": "Rosa Spencer"
    },
    {
        "kod": "595633201d62fc0328a49ae4",
        "popis": "Baldwin Sears"
    },
    {
        "kod": "5956332094c6052275a52474",
        "popis": "Myrna Glass"
    },
    {
        "kod": "59563320e968583168b3d6b9",
        "popis": "Jane Giles"
    },
    {
        "kod": "59563320ed0cc7fcf89895e4",
        "popis": "Mitzi Kaufman"
    },
    {
        "kod": "5956332045d51afd36a038da",
        "popis": "Avila Schroeder"
    },
    {
        "kod": "59563320b2b2b2fcd5281c3e",
        "popis": "Whitley Mcgee"
    },
    {
        "kod": "59563320fcd5a4048123c684",
        "popis": "Lauren Randolph"
    },
    {
        "kod": "595633200dfd3e8b01ec8efb",
        "popis": "Booker Erickson"
    },
    {
        "kod": "59563320b2418dbf5e520c21",
        "popis": "Walters Miles"
    },
    {
        "kod": "595633201a490fa75d0cbe36",
        "popis": "Koch Maynard"
    },
    {
        "kod": "59563320ddf411c50de75d2f",
        "popis": "Olive Madden"
    },
    {
        "kod": "5956332044ab228e62c299fe",
        "popis": "Mooney Bray"
    },
    {
        "kod": "595633204b18852458956ed9",
        "popis": "Angelina Moss"
    },
    {
        "kod": "5956332062f4a55561fb6bfa",
        "popis": "Malone Hooper"
    },
    {
        "kod": "5956332073f36c40632be0ad",
        "popis": "Merritt Stark"
    },
    {
        "kod": "5956332011da49d9b01b0ef4",
        "popis": "Jillian Allison"
    },
    {
        "kod": "59563320a94c207fb3152e60",
        "popis": "Nichols Sosa"
    },
    {
        "kod": "59563320c665c0cb533f7e44",
        "popis": "Jan Fulton"
    },
    {
        "kod": "595633202cac7505eafffd82",
        "popis": "Bryant Mcmillan"
    },
    {
        "kod": "595633209ac614239526077d",
        "popis": "Wiley Gilliam"
    },
    {
        "kod": "59563320e8ec520816e539a0",
        "popis": "Nannie Chapman"
    },
    {
        "kod": "59563320500b05784a684c10",
        "popis": "Moran Mcdonald"
    },
    {
        "kod": "59563320d8f0d6e6603924b1",
        "popis": "Lorna Wiley"
    },
    {
        "kod": "59563320846db5bd5121dfad",
        "popis": "Norman Finley"
    },
    {
        "kod": "59563320fd12a1ea2a05e552",
        "popis": "Therese Atkinson"
    }
]